Metadata-Version: 2.1
Name: micropython-httpota
Version: 0.1.15
Summary: MicroPython library for OTA updates using HTTP
Home-page: https://github.com/leprechaun/micropython-http-ota
Author: Leprechaun
Author-email: leprechaun@gmail.com
Maintainer: Leprechaun
Maintainer-email: leprechaun@gmail.com
License: MIT
Keywords: micropython OTA http
Platform: UNKNOWN
Classifier: Development Status :: 3 - Alpha
Classifier: Programming Language :: Python :: Implementation :: MicroPython
Classifier: License :: OSI Approved :: MIT License
